tango_ext/__init__.py
tango_ext/common/__init__.py
tango_ext/common/testing/__init__.py
tango_ext/integrations/__init__.py
tango_ext/integrations/albumentations/__init__.py
tango_ext/integrations/albumentations/core/__init__.py
tango_ext/integrations/albumentations/core/composition.py
tango_ext/integrations/albumentations/core/utils.py
tango_ext/integrations/albumentations/transforms.py
tango_ext/integrations/diffusers/__init__.py
tango_ext/integrations/diffusers/format.py
tango_extensions-0.3.0.dist-info/LICENSE
tango_extensions-0.3.0.dist-info/METADATA
tango_extensions-0.3.0.dist-info/WHEEL
tango_extensions-0.3.0.dist-info/RECORD
