Metadata-Version: 2.1
Name: tango-extensions
Version: 0.3.0
Summary: Extension modules for allenai/tango (ai2-tango)
Author: Shunsuke KITADA
Author-email: shunsuke.kitada.0831@gmail.com
Requires-Python: >=3.9,<4.0
Classifier: Programming Language :: Python :: 3
Classifier: Programming Language :: Python :: 3.9
Classifier: Programming Language :: Python :: 3.10
Classifier: Programming Language :: Python :: 3.11
Provides-Extra: albumentations
Provides-Extra: all
Provides-Extra: diffusers
Requires-Dist: accelerate (>=0.22.0,<0.23.0) ; extra == "diffusers" or extra == "all"
Requires-Dist: ai2-tango[datasets,examples,torch,transformers,wandb] (>=1.0.0)
Requires-Dist: albumentations (>=1.0.0) ; extra == "albumentations" or extra == "all"
Requires-Dist: diffusers (>=0.18.0) ; extra == "diffusers" or extra == "all"
Requires-Dist: torch (>=1.9.0,!=2.0.1) ; extra == "diffusers" or extra == "all"
Requires-Dist: torchvision (>=0.9.0) ; extra == "albumentations" or extra == "all"
Requires-Dist: urllib3 (<2)
